isocountry/__init__.py
isocountry/db.py
isocountry/py.typed
isocountry/databases/iso15924.json
isocountry/databases/iso3166-1.json
isocountry/databases/iso3166-2.json
isocountry/databases/iso3166-3.json
isocountry/databases/iso4217.json
isocountry/databases/iso639-3.json
isocountry/databases/iso639-5.json
isocountry/locales/ab/LC_MESSAGES/iso3166-1.mo
isocountry/locales/ab/LC_MESSAGES/iso639-5.mo
isocountry/locales/ace/LC_MESSAGES/iso3166-1.mo
isocountry/locales/ach/LC_MESSAGES/iso3166-1.mo
isocountry/locales/af/LC_MESSAGES/iso3166-1.mo
isocountry/locales/af/LC_MESSAGES/iso3166-3.mo
isocountry/locales/af/LC_MESSAGES/iso639-3.mo
isocountry/locales/ak/LC_MESSAGES/iso3166-1.mo
isocountry/locales/am/LC_MESSAGES/iso3166-1.mo
isocountry/locales/am/LC_MESSAGES/iso3166-3.mo
isocountry/locales/am/LC_MESSAGES/iso639-3.mo
isocountry/locales/an/LC_MESSAGES/iso3166-1.mo
isocountry/locales/ar/LC_MESSAGES/iso15924.mo
isocountry/locales/ar/LC_MESSAGES/iso3166-1.mo
isocountry/locales/ar/LC_MESSAGES/iso3166-3.mo
isocountry/locales/ar/LC_MESSAGES/iso4217.mo
isocountry/locales/ar/LC_MESSAGES/iso639-3.mo
isocountry/locales/as/LC_MESSAGES/iso3166-1.mo
isocountry/locales/as/LC_MESSAGES/iso3166-3.mo
isocountry/locales/ast/LC_MESSAGES/iso15924.mo
isocountry/locales/ast/LC_MESSAGES/iso3166-1.mo
isocountry/locales/ast/LC_MESSAGES/iso3166-2.mo
isocountry/locales/ast/LC_MESSAGES/iso3166-3.mo
isocountry/locales/ast/LC_MESSAGES/iso4217.mo
isocountry/locales/ast/LC_MESSAGES/iso639-3.mo
isocountry/locales/ast/LC_MESSAGES/iso639-5.mo
isocountry/locales/ay/LC_MESSAGES/iso3166-1.mo
isocountry/locales/az/LC_MESSAGES/iso3166-1.mo
isocountry/locales/az/LC_MESSAGES/iso3166-2.mo
isocountry/locales/az/LC_MESSAGES/iso3166-3.mo
isocountry/locales/az/LC_MESSAGES/iso639-3.mo
isocountry/locales/ba/LC_MESSAGES/iso3166-1.mo
isocountry/locales/bar/LC_MESSAGES/iso3166-1.mo
isocountry/locales/be/LC_MESSAGES/iso15924.mo
isocountry/locales/be/LC_MESSAGES/iso3166-1.mo
isocountry/locales/be/LC_MESSAGES/iso3166-2.mo
isocountry-23.2.0.dist-info/METADATA
isocountry-23.2.0.dist-info/WHEEL
isocountry-23.2.0.dist-info/licenses/LICENSE
isocountry-23.2.0.dist-info/RECORD
