Metadata-Version: 2.1
Name: isocountry
Version: 23.2.0
Summary: ISO country, subdivision, language, currency and script definitions and their translations
Project-URL: Homepage, https://github.com/yezz123/isocountry
Project-URL: Documentation, https://github.com/yezz123/isocountry/blob/main/README.md
Author-email: Yasser Tahiri <hello@yezz.me>, Christian Theune <ct@flyingcircus.io>
License-File: LICENSE
Keywords: 15924,3166,3166-2,4217,639,country,currency,iso,language,subdivision
Classifier: Development Status :: 5 - Production/Stable
Classifier: Intended Audience :: Developers
Classifier: Intended Audience :: Information Technology
Classifier: License :: OSI Approved :: GNU Lesser General Public License v2 (LGPLv2)
Classifier: Operating System :: OS Independent
Classifier: Programming Language :: Python
Classifier: Programming Language :: Python :: 3
Classifier: Programming Language :: Python :: 3 :: Only
Classifier: Programming Language :: Python :: 3.8
Classifier: Programming Language :: Python :: 3.9
Classifier: Programming Language :: Python :: 3.10
Classifier: Programming Language :: Python :: 3.11
Classifier: Programming Language :: Python :: 3.12
Classifier: Topic :: Software Development :: Internationalization
Classifier: Topic :: Software Development :: Libraries :: Python Modules
Classifier: Topic :: Software Development :: Localization
Classifier: Typing :: Typed
Requires-Python: >=3.8
Requires-Dist: importlib-resources<6.0.0,>=5.4.0
Provides-Extra: lint
Requires-Dist: pre-commit==3.3.3; extra == 'lint'
Provides-Extra: test
Requires-Dist: pytest-asyncio==0.21.1; extra == 'test'
Requires-Dist: pytest-cov==4.1.0; extra == 'test'
Requires-Dist: pytest-pretty==1.2.0; extra == 'test'
Requires-Dist: pytest==7.4.0; extra == 'test'
Requires-Dist: python-decouple; extra == 'test'
